{
    "price": {
        "current": {
            "datetime": "2022-12-15 00:00:00",
            "count": 3.0,
            "mean": 3066.6666666666665,
            "std": 1616.580753730952,
            "min": 1200.0,
            "25%": 2600.0,
            "50%": 4000.0,
            "75%": 4000.0,
            "max": 4000.0
        },
        "summary7Days": {
            "datetime": "2022-12-15 00:00:00",
            "count": 0.0,
            "mean": -600.0,
            "std": 1039.2304845413262,
            "min": -1800.0,
            "25%": -900.0,
            "50%": 0.0,
            "75%": 0.0,
            "max": 0.0
        },
        "volatility": {
            "weekly": {
                "min": {
                    "basePrice": 3000.0,
                    "latestPrice": 1200.0,
                    "percent": -60.0
                },
                "50%": {
                    "basePrice": 4000.0,
                    "latestPrice": 4000.0,
                    "percent": 0.0
                }
            },
            "daily": {
                "min": {
                    "basePrice": 1400.0,
                    "latestPrice": 1200.0,
                    "percent": -14.29
                },
                "50%": {
                    "basePrice": 3759.0,
                    "latestPrice": 4000.0,
                    "percent": 6.41
                }
            }
        },
        "weekly": {
            "archive": {
                "count": 7,
                "data": [
                    {
                        "datetime": "2022-12-09 00:00:00",
                        "count": 3.0,
                        "mean": 3666.6666666666665,
                        "std": 577.3502691896258,
                        "min": 3000.0,
                        "25%": 3500.0,
                        "50%": 4000.0,
                        "75%": 4000.0,
                        "max": 4000.0
                    },
                    {
                        "datetime": "2022-12-10 00:00:00",
                        "count": 2.0,
                        "mean": 4000.0,
                        "std": 0.0,
                        "min": 4000.0,
                        "25%": 4000.0,
                        "50%": 4000.0,
                        "75%": 4000.0,
                        "max": 4000.0
                    },
                    {
                        "datetime": "2022-12-11 00:00:00",
                        "count": 6.0,
                        "mean": 3453.1666666666665,
                        "std": 831.4710858873366,
                        "min": 1800.0,
                        "25%": 3580.0,
                        "50%": 3669.5,
                        "75%": 3939.75,
                        "max": 4000.0
                    },
                    {
                        "datetime": "2022-12-12 00:00:00",
                        "count": 6.0,
                        "mean": 3419.833333333333,
                        "std": 911.1883266738369,
                        "min": 1600.0,
                        "25%": 3580.0,
                        "50%": 3669.5,
                        "75%": 3939.75,
                        "max": 4000.0
                    },
                    {
                        "datetime": "2022-12-13 00:00:00",
                        "count": 3.0,
                        "mean": 3200.0,
                        "std": 1385.6406460551018,
                        "min": 1600.0,
                        "25%": 2800.0,
                        "50%": 4000.0,
                        "75%": 4000.0,
                        "max": 4000.0
                    },
                    {
                        "datetime": "2022-12-14 00:00:00",
                        "count": 5.0,
                        "mean": 3347.8,
                        "std": 1103.138341279098,
                        "min": 1400.0,
                        "25%": 3580.0,
                        "50%": 3759.0,
                        "75%": 4000.0,
                        "max": 4000.0
                    },
                    {
                        "datetime": "2022-12-15 00:00:00",
                        "count": 3.0,
                        "mean": 3066.6666666666665,
                        "std": 1616.580753730952,
                        "min": 1200.0,
                        "25%": 2600.0,
                        "50%": 4000.0,
                        "75%": 4000.0,
                        "max": 4000.0
                    }
                ]
            },
            "diff": {
                "count": 7,
                "data": [
                    {
                        "datetime": "2022-12-09 00:00:00",
                        "count": null,
                        "mean": null,
                        "std": null,
                        "min": null,
                        "25%": null,
                        "50%": null,
                        "75%": null,
                        "max": null
                    },
                    {
                        "datetime": "2022-12-10 00:00:00",
                        "count": -1.0,
                        "mean": 333.3333333333335,
                        "std": -577.3502691896258,
                        "min": 1000.0,
                        "25%": 500.0,
                        "50%": 0.0,
                        "75%": 0.0,
                        "max": 0.0
                    },
                    {
                        "datetime": "2022-12-11 00:00:00",
                        "count": 4.0,
                        "mean": -546.8333333333335,
                        "std": 831.4710858873366,
                        "min": -2200.0,
                        "25%": -420.0,
                        "50%": -330.5,
                        "75%": -60.25,
                        "max": 0.0
                    },
                    {
                        "datetime": "2022-12-12 00:00:00",
                        "count": 0.0,
                        "mean": -33.333333333333485,
                        "std": 79.71724078650027,
                        "min": -200.0,
                        "25%": 0.0,
                        "50%": 0.0,
                        "75%": 0.0,
                        "max": 0.0
                    },
                    {
                        "datetime": "2022-12-13 00:00:00",
                        "count": -3.0,
                        "mean": -219.83333333333303,
                        "std": 474.45231938126494,
                        "min": 0.0,
                        "25%": -780.0,
                        "50%": 330.5,
                        "75%": 60.25,
                        "max": 0.0
                    },
                    {
                        "datetime": "2022-12-14 00:00:00",
                        "count": 2.0,
                        "mean": 147.80000000000018,
                        "std": -282.5023047760037,
                        "min": -200.0,
                        "25%": 780.0,
                        "50%": -241.0,
                        "75%": 0.0,
                        "max": 0.0
                    },
                    {
                        "datetime": "2022-12-15 00:00:00",
                        "count": -2.0,
                        "mean": -281.13333333333367,
                        "std": 513.4424124518539,
                        "min": -200.0,
                        "25%": -980.0,
                        "50%": 241.0,
                        "75%": 0.0,
                        "max": 0.0
                    }
                ]
            }
        },
        "halfYear": {
            "archive": {
                "count": 13,
                "data": [
                    {
                        "datetime": "2022-06-30 00:00:00",
                        "count": 0.0,
                        "mean": 0.0,
                        "std": 0.0,
                        "min": 0.0,
                        "25%": 0.0,
                        "50%": 0.0,
                        "75%": 0.0,
                        "max": 0.0
                    },
                    {
                        "datetime": "2022-07-14 00:00:00",
                        "count": 0.0,
                        "mean": 0.0,
                        "std": 0.0,
                        "min": 0.0,
                        "25%": 0.0,
                        "50%": 0.0,
                        "75%": 0.0,
                        "max": 0.0
                    },
                    {
                        "datetime": "2022-07-28 00:00:00",
                        "count": 0.0,
                        "mean": 0.0,
                        "std": 0.0,
                        "min": 0.0,
                        "25%": 0.0,
                        "50%": 0.0,
                        "75%": 0.0,
                        "max": 0.0
                    },
                    {
                        "datetime": "2022-08-11 00:00:00",
                        "count": 0.0,
                        "mean": 0.0,
                        "std": 0.0,
                        "min": 0.0,
                        "25%": 0.0,
                        "50%": 0.0,
                        "75%": 0.0,
                        "max": 0.0
                    },
                    {
                        "datetime": "2022-08-25 00:00:00",
                        "count": 9.0,
                        "mean": 2313.333333333333,
                        "std": 200.0,
                        "min": 1780.0,
                        "25%": 2380.0,
                        "50%": 2380.0,
                        "75%": 2380.0,
                        "max": 2380.0
                    },
                    {
                        "datetime": "2022-09-08 00:00:00",
                        "count": 10.0,
                        "mean": 2429.9,
                        "std": 262.3782045487434,
                        "min": 1720.0,
                        "25%": 2480.0,
                        "50%": 2480.0,
                        "75%": 2480.0,
                        "max": 2739.0
                    },
                    {
                        "datetime": "2022-09-22 00:00:00",
                        "count": 23.0,
                        "mean": 2592.5652173913045,
                        "std": 366.9375505558203,
                        "min": 1290.0,
                        "25%": 2480.0,
                        "50%": 2480.0,
                        "75%": 2980.0,
                        "max": 3000.0
                    },
                    {
                        "datetime": "2022-10-06 00:00:00",
                        "count": 60.0,
                        "mean": 2639.9333333333334,
                        "std": 266.13886184717694,
                        "min": 1980.0,
                        "25%": 2480.0,
                        "50%": 2480.0,
                        "75%": 2980.0,
                        "max": 3000.0
                    },
                    {
                        "datetime": "2022-10-20 00:00:00",
                        "count": 17.0,
                        "mean": 2839.9411764705883,
                        "std": 247.1438019120233,
                        "min": 2780.0,
                        "25%": 2780.0,
                        "50%": 2780.0,
                        "75%": 2780.0,
                        "max": 3799.0
                    },
                    {
                        "datetime": "2022-11-03 00:00:00",
                        "count": 2.0,
                        "mean": 3272.0,
                        "std": 243.24473272817235,
                        "min": 3100.0,
                        "25%": 3186.0,
                        "50%": 3272.0,
                        "75%": 3358.0,
                        "max": 3444.0
                    },
                    {
                        "datetime": "2022-11-17 00:00:00",
                        "count": 11.0,
                        "mean": 2952.6363636363635,
                        "std": 418.6889711294704,
                        "min": 2380.0,
                        "25%": 2880.0,
                        "50%": 2880.0,
                        "75%": 2990.0,
                        "max": 3759.0
                    },
                    {
                        "datetime": "2022-12-01 00:00:00",
                        "count": 9.0,
                        "mean": 3515.4444444444443,
                        "std": 333.79151843295506,
                        "min": 2880.0,
                        "25%": 3580.0,
                        "50%": 3580.0,
                        "75%": 3580.0,
                        "max": 4000.0
                    },
                    {
                        "datetime": "2022-12-15 00:00:00",
                        "count": 3.0,
                        "mean": 3066.6666666666665,
                        "std": 1616.580753730952,
                        "min": 1200.0,
                        "25%": 2600.0,
                        "50%": 4000.0,
                        "75%": 4000.0,
                        "max": 4000.0
                    }
                ]
            },
            "diff": {
                "count": 13,
                "data": [
                    {
                        "datetime": "2022-06-30 00:00:00",
                        "count": null,
                        "mean": null,
                        "std": null,
                        "min": null,
                        "25%": null,
                        "50%": null,
                        "75%": null,
                        "max": null
                    },
                    {
                        "datetime": "2022-07-14 00:00:00",
                        "count": 0.0,
                        "mean": 0.0,
                        "std": 0.0,
                        "min": 0.0,
                        "25%": 0.0,
                        "50%": 0.0,
                        "75%": 0.0,
                        "max": 0.0
                    },
                    {
                        "datetime": "2022-07-28 00:00:00",
                        "count": 0.0,
                        "mean": 0.0,
                        "std": 0.0,
                        "min": 0.0,
                        "25%": 0.0,
                        "50%": 0.0,
                        "75%": 0.0,
                        "max": 0.0
                    },
                    {
                        "datetime": "2022-08-11 00:00:00",
                        "count": 0.0,
                        "mean": 0.0,
                        "std": 0.0,
                        "min": 0.0,
                        "25%": 0.0,
                        "50%": 0.0,
                        "75%": 0.0,
                        "max": 0.0
                    },
                    {
                        "datetime": "2022-08-25 00:00:00",
                        "count": 9.0,
                        "mean": 2313.333333333333,
                        "std": 200.0,
                        "min": 1780.0,
                        "25%": 2380.0,
                        "50%": 2380.0,
                        "75%": 2380.0,
                        "max": 2380.0
                    },
                    {
                        "datetime": "2022-09-08 00:00:00",
                        "count": 1.0,
                        "mean": 116.56666666666706,
                        "std": 62.37820454874338,
                        "min": -60.0,
                        "25%": 100.0,
                        "50%": 100.0,
                        "75%": 100.0,
                        "max": 359.0
                    },
                    {
                        "datetime": "2022-09-22 00:00:00",
                        "count": 13.0,
                        "mean": 162.6652173913044,
                        "std": 104.5593460070769,
                        "min": -430.0,
                        "25%": 0.0,
                        "50%": 0.0,
                        "75%": 500.0,
                        "max": 261.0
                    },
                    {
                        "datetime": "2022-10-06 00:00:00",
                        "count": 37.0,
                        "mean": 47.36811594202891,
                        "std": -100.79868870864334,
                        "min": 690.0,
                        "25%": 0.0,
                        "50%": 0.0,
                        "75%": 0.0,
                        "max": 0.0
                    },
                    {
                        "datetime": "2022-10-20 00:00:00",
                        "count": -43.0,
                        "mean": 200.0078431372549,
                        "std": -18.995059935153648,
                        "min": 800.0,
                        "25%": 300.0,
                        "50%": 300.0,
                        "75%": -200.0,
                        "max": 799.0
                    },
                    {
                        "datetime": "2022-11-03 00:00:00",
                        "count": -15.0,
                        "mean": 432.0588235294117,
                        "std": -3.8990691838509406,
                        "min": 320.0,
                        "25%": 406.0,
                        "50%": 492.0,
                        "75%": 578.0,
                        "max": -355.0
                    },
                    {
                        "datetime": "2022-11-17 00:00:00",
                        "count": 9.0,
                        "mean": -319.3636363636365,
                        "std": 175.44423840129807,
                        "min": -720.0,
                        "25%": -306.0,
                        "50%": -392.0,
                        "75%": -368.0,
                        "max": 315.0
                    },
                    {
                        "datetime": "2022-12-01 00:00:00",
                        "count": -2.0,
                        "mean": 562.8080808080808,
                        "std": -84.89745269651536,
                        "min": 500.0,
                        "25%": 700.0,
                        "50%": 700.0,
                        "75%": 590.0,
                        "max": 241.0
                    },
                    {
                        "datetime": "2022-12-15 00:00:00",
                        "count": -6.0,
                        "mean": -448.7777777777778,
                        "std": 1282.789235297997,
                        "min": -1680.0,
                        "25%": -980.0,
                        "50%": 420.0,
                        "75%": 420.0,
                        "max": 0.0
                    }
                ]
            }
        },
        "OneYear": {
            "archive": {
                "count": 0,
                "data": []
            },
            "diff": {
                "count": 0,
                "data": []
            }
        }
    },
    "calc": {
        "latest_date": "2022-12-15 00:00:00",
        "updated_at": "2022-12-15 20:01:40"
    }
}