{
    "price": {
        "current": {
            "datetime": "2022-11-21 00:00:00",
            "count": 72.0,
            "mean": 146.25,
            "std": 42.60653590012277,
            "min": 120.0,
            "25%": 120.0,
            "50%": 120.0,
            "75%": 200.0,
            "max": 330.0
        },
        "summary7Days": {
            "datetime": "2022-11-21 00:00:00",
            "count": 2.0,
            "mean": 2.25,
            "std": 5.681229389958702,
            "min": 0.0,
            "25%": 0.0,
            "50%": 0.0,
            "75%": 0.0,
            "max": 130.0
        },
        "volatility": {
            "weekly": {
                "min": {
                    "basePrice": 120.0,
                    "latestPrice": 120.0,
                    "percent": 0.0
                },
                "50%": {
                    "basePrice": 120.0,
                    "latestPrice": 120.0,
                    "percent": 0.0
                }
            },
            "daily": {
                "min": {
                    "basePrice": 120.0,
                    "latestPrice": 120.0,
                    "percent": 0.0
                },
                "50%": {
                    "basePrice": 120.0,
                    "latestPrice": 120.0,
                    "percent": 0.0
                }
            }
        },
        "weekly": {
            "archive": {
                "count": 7,
                "data": [
                    {
                        "datetime": "2022-11-15 00:00:00",
                        "count": 70.0,
                        "mean": 144.0,
                        "std": 36.92530651016407,
                        "min": 120.0,
                        "25%": 120.0,
                        "50%": 120.0,
                        "75%": 200.0,
                        "max": 200.0
                    },
                    {
                        "datetime": "2022-11-16 00:00:00",
                        "count": 71.0,
                        "mean": 146.61971830985917,
                        "std": 42.793312627486586,
                        "min": 120.0,
                        "25%": 120.0,
                        "50%": 120.0,
                        "75%": 200.0,
                        "max": 330.0
                    },
                    {
                        "datetime": "2022-11-17 00:00:00",
                        "count": 71.0,
                        "mean": 146.61971830985917,
                        "std": 42.793312627486586,
                        "min": 120.0,
                        "25%": 120.0,
                        "50%": 120.0,
                        "75%": 200.0,
                        "max": 330.0
                    },
                    {
                        "datetime": "2022-11-18 00:00:00",
                        "count": 71.0,
                        "mean": 146.61971830985917,
                        "std": 42.793312627486586,
                        "min": 120.0,
                        "25%": 120.0,
                        "50%": 120.0,
                        "75%": 200.0,
                        "max": 330.0
                    },
                    {
                        "datetime": "2022-11-19 00:00:00",
                        "count": 71.0,
                        "mean": 146.61971830985917,
                        "std": 42.793312627486586,
                        "min": 120.0,
                        "25%": 120.0,
                        "50%": 120.0,
                        "75%": 200.0,
                        "max": 330.0
                    },
                    {
                        "datetime": "2022-11-20 00:00:00",
                        "count": 72.0,
                        "mean": 146.25,
                        "std": 42.60653590012277,
                        "min": 120.0,
                        "25%": 120.0,
                        "50%": 120.0,
                        "75%": 200.0,
                        "max": 330.0
                    },
                    {
                        "datetime": "2022-11-21 00:00:00",
                        "count": 72.0,
                        "mean": 146.25,
                        "std": 42.60653590012277,
                        "min": 120.0,
                        "25%": 120.0,
                        "50%": 120.0,
                        "75%": 200.0,
                        "max": 330.0
                    }
                ]
            },
            "diff": {
                "count": 7,
                "data": [
                    {
                        "datetime": "2022-11-15 00:00:00",
                        "count": null,
                        "mean": null,
                        "std": null,
                        "min": null,
                        "25%": null,
                        "50%": null,
                        "75%": null,
                        "max": null
                    },
                    {
                        "datetime": "2022-11-16 00:00:00",
                        "count": 1.0,
                        "mean": 2.6197183098591665,
                        "std": 5.8680061173225155,
                        "min": 0.0,
                        "25%": 0.0,
                        "50%": 0.0,
                        "75%": 0.0,
                        "max": 130.0
                    },
                    {
                        "datetime": "2022-11-17 00:00:00",
                        "count": 0.0,
                        "mean": 0.0,
                        "std": 0.0,
                        "min": 0.0,
                        "25%": 0.0,
                        "50%": 0.0,
                        "75%": 0.0,
                        "max": 0.0
                    },
                    {
                        "datetime": "2022-11-18 00:00:00",
                        "count": 0.0,
                        "mean": 0.0,
                        "std": 0.0,
                        "min": 0.0,
                        "25%": 0.0,
                        "50%": 0.0,
                        "75%": 0.0,
                        "max": 0.0
                    },
                    {
                        "datetime": "2022-11-19 00:00:00",
                        "count": 0.0,
                        "mean": 0.0,
                        "std": 0.0,
                        "min": 0.0,
                        "25%": 0.0,
                        "50%": 0.0,
                        "75%": 0.0,
                        "max": 0.0
                    },
                    {
                        "datetime": "2022-11-20 00:00:00",
                        "count": 1.0,
                        "mean": -0.36971830985916654,
                        "std": -0.18677672736381368,
                        "min": 0.0,
                        "25%": 0.0,
                        "50%": 0.0,
                        "75%": 0.0,
                        "max": 0.0
                    },
                    {
                        "datetime": "2022-11-21 00:00:00",
                        "count": 0.0,
                        "mean": 0.0,
                        "std": 0.0,
                        "min": 0.0,
                        "25%": 0.0,
                        "50%": 0.0,
                        "75%": 0.0,
                        "max": 0.0
                    }
                ]
            }
        },
        "halfYear": {
            "archive": {
                "count": 13,
                "data": [
                    {
                        "datetime": "2022-06-06 00:00:00",
                        "count": 0.0,
                        "mean": 0.0,
                        "std": 0.0,
                        "min": 0.0,
                        "25%": 0.0,
                        "50%": 0.0,
                        "75%": 0.0,
                        "max": 0.0
                    },
                    {
                        "datetime": "2022-06-20 00:00:00",
                        "count": 0.0,
                        "mean": 0.0,
                        "std": 0.0,
                        "min": 0.0,
                        "25%": 0.0,
                        "50%": 0.0,
                        "75%": 0.0,
                        "max": 0.0
                    },
                    {
                        "datetime": "2022-07-04 00:00:00",
                        "count": 0.0,
                        "mean": 0.0,
                        "std": 0.0,
                        "min": 0.0,
                        "25%": 0.0,
                        "50%": 0.0,
                        "75%": 0.0,
                        "max": 0.0
                    },
                    {
                        "datetime": "2022-07-18 00:00:00",
                        "count": 0.0,
                        "mean": 0.0,
                        "std": 0.0,
                        "min": 0.0,
                        "25%": 0.0,
                        "50%": 0.0,
                        "75%": 0.0,
                        "max": 0.0
                    },
                    {
                        "datetime": "2022-08-01 00:00:00",
                        "count": 0.0,
                        "mean": 0.0,
                        "std": 0.0,
                        "min": 0.0,
                        "25%": 0.0,
                        "50%": 0.0,
                        "75%": 0.0,
                        "max": 0.0
                    },
                    {
                        "datetime": "2022-08-15 00:00:00",
                        "count": 0.0,
                        "mean": 0.0,
                        "std": 0.0,
                        "min": 0.0,
                        "25%": 0.0,
                        "50%": 0.0,
                        "75%": 0.0,
                        "max": 0.0
                    },
                    {
                        "datetime": "2022-08-29 00:00:00",
                        "count": 124.0,
                        "mean": 98.38709677419357,
                        "std": 43.39995685386552,
                        "min": 80.0,
                        "25%": 80.0,
                        "50%": 80.0,
                        "75%": 80.0,
                        "max": 200.0
                    },
                    {
                        "datetime": "2022-09-12 00:00:00",
                        "count": 114.0,
                        "mean": 97.89473684210526,
                        "std": 42.93385907695544,
                        "min": 80.0,
                        "25%": 80.0,
                        "50%": 80.0,
                        "75%": 80.0,
                        "max": 200.0
                    },
                    {
                        "datetime": "2022-09-26 00:00:00",
                        "count": 62.0,
                        "mean": 107.09677419354838,
                        "std": 50.58306256971578,
                        "min": 80.0,
                        "25%": 80.0,
                        "50%": 80.0,
                        "75%": 80.0,
                        "max": 200.0
                    },
                    {
                        "datetime": "2022-10-10 00:00:00",
                        "count": 57.0,
                        "mean": 107.36842105263158,
                        "std": 50.79814098783093,
                        "min": 80.0,
                        "25%": 80.0,
                        "50%": 80.0,
                        "75%": 80.0,
                        "max": 200.0
                    },
                    {
                        "datetime": "2022-10-24 00:00:00",
                        "count": 60.0,
                        "mean": 106.0,
                        "std": 49.854024198790206,
                        "min": 80.0,
                        "25%": 80.0,
                        "50%": 80.0,
                        "75%": 80.0,
                        "max": 200.0
                    },
                    {
                        "datetime": "2022-11-07 00:00:00",
                        "count": 61.0,
                        "mean": 137.04918032786884,
                        "std": 33.03252247382278,
                        "min": 120.0,
                        "25%": 120.0,
                        "50%": 120.0,
                        "75%": 120.0,
                        "max": 200.0
                    },
                    {
                        "datetime": "2022-11-21 00:00:00",
                        "count": 72.0,
                        "mean": 146.25,
                        "std": 42.60653590012277,
                        "min": 120.0,
                        "25%": 120.0,
                        "50%": 120.0,
                        "75%": 200.0,
                        "max": 330.0
                    }
                ]
            },
            "diff": {
                "count": 13,
                "data": [
                    {
                        "datetime": "2022-06-06 00:00:00",
                        "count": null,
                        "mean": null,
                        "std": null,
                        "min": null,
                        "25%": null,
                        "50%": null,
                        "75%": null,
                        "max": null
                    },
                    {
                        "datetime": "2022-06-20 00:00:00",
                        "count": 0.0,
                        "mean": 0.0,
                        "std": 0.0,
                        "min": 0.0,
                        "25%": 0.0,
                        "50%": 0.0,
                        "75%": 0.0,
                        "max": 0.0
                    },
                    {
                        "datetime": "2022-07-04 00:00:00",
                        "count": 0.0,
                        "mean": 0.0,
                        "std": 0.0,
                        "min": 0.0,
                        "25%": 0.0,
                        "50%": 0.0,
                        "75%": 0.0,
                        "max": 0.0
                    },
                    {
                        "datetime": "2022-07-18 00:00:00",
                        "count": 0.0,
                        "mean": 0.0,
                        "std": 0.0,
                        "min": 0.0,
                        "25%": 0.0,
                        "50%": 0.0,
                        "75%": 0.0,
                        "max": 0.0
                    },
                    {
                        "datetime": "2022-08-01 00:00:00",
                        "count": 0.0,
                        "mean": 0.0,
                        "std": 0.0,
                        "min": 0.0,
                        "25%": 0.0,
                        "50%": 0.0,
                        "75%": 0.0,
                        "max": 0.0
                    },
                    {
                        "datetime": "2022-08-15 00:00:00",
                        "count": 0.0,
                        "mean": 0.0,
                        "std": 0.0,
                        "min": 0.0,
                        "25%": 0.0,
                        "50%": 0.0,
                        "75%": 0.0,
                        "max": 0.0
                    },
                    {
                        "datetime": "2022-08-29 00:00:00",
                        "count": 124.0,
                        "mean": 98.38709677419357,
                        "std": 43.39995685386552,
                        "min": 80.0,
                        "25%": 80.0,
                        "50%": 80.0,
                        "75%": 80.0,
                        "max": 200.0
                    },
                    {
                        "datetime": "2022-09-12 00:00:00",
                        "count": -10.0,
                        "mean": -0.49235993208830564,
                        "std": -0.46609777691007537,
                        "min": 0.0,
                        "25%": 0.0,
                        "50%": 0.0,
                        "75%": 0.0,
                        "max": 0.0
                    },
                    {
                        "datetime": "2022-09-26 00:00:00",
                        "count": -52.0,
                        "mean": 9.202037351443124,
                        "std": 7.649203492760336,
                        "min": 0.0,
                        "25%": 0.0,
                        "50%": 0.0,
                        "75%": 0.0,
                        "max": 0.0
                    },
                    {
                        "datetime": "2022-10-10 00:00:00",
                        "count": -5.0,
                        "mean": 0.27164685908319086,
                        "std": 0.21507841811514794,
                        "min": 0.0,
                        "25%": 0.0,
                        "50%": 0.0,
                        "75%": 0.0,
                        "max": 0.0
                    },
                    {
                        "datetime": "2022-10-24 00:00:00",
                        "count": 3.0,
                        "mean": -1.3684210526315752,
                        "std": -0.94411678904072,
                        "min": 0.0,
                        "25%": 0.0,
                        "50%": 0.0,
                        "75%": 0.0,
                        "max": 0.0
                    },
                    {
                        "datetime": "2022-11-07 00:00:00",
                        "count": 1.0,
                        "mean": 31.04918032786884,
                        "std": -16.821501724967426,
                        "min": 40.0,
                        "25%": 40.0,
                        "50%": 40.0,
                        "75%": 40.0,
                        "max": 0.0
                    },
                    {
                        "datetime": "2022-11-21 00:00:00",
                        "count": 11.0,
                        "mean": 9.20081967213116,
                        "std": 9.574013426299992,
                        "min": 0.0,
                        "25%": 0.0,
                        "50%": 0.0,
                        "75%": 80.0,
                        "max": 130.0
                    }
                ]
            }
        },
        "OneYear": {
            "archive": {
                "count": 0,
                "data": []
            },
            "diff": {
                "count": 0,
                "data": []
            }
        }
    },
    "calc": {
        "latest_date": "2022-11-21 00:00:00",
        "updated_at": "2022-11-21 20:02:37"
    }
}