{
    "price": {
        "current": {
            "datetime": "2022-12-02 00:00:00",
            "count": 115.0,
            "mean": 179.30434782608697,
            "std": 76.2696249019554,
            "min": 150.0,
            "25%": 150.0,
            "50%": 150.0,
            "75%": 150.0,
            "max": 420.0
        },
        "summary7Days": {
            "datetime": "2022-12-02 00:00:00",
            "count": 12.0,
            "mean": -4.190797804981031,
            "std": -2.6161045396705305,
            "min": 0.0,
            "25%": 0.0,
            "50%": 0.0,
            "75%": 0.0,
            "max": 0.0
        },
        "volatility": {
            "weekly": {
                "min": {
                    "basePrice": 150.0,
                    "latestPrice": 150.0,
                    "percent": 0.0
                },
                "50%": {
                    "basePrice": 150.0,
                    "latestPrice": 150.0,
                    "percent": 0.0
                }
            },
            "daily": {
                "min": {
                    "basePrice": 150.0,
                    "latestPrice": 150.0,
                    "percent": 0.0
                },
                "50%": {
                    "basePrice": 150.0,
                    "latestPrice": 150.0,
                    "percent": 0.0
                }
            }
        },
        "weekly": {
            "archive": {
                "count": 7,
                "data": [
                    {
                        "datetime": "2022-11-26 00:00:00",
                        "count": 103.0,
                        "mean": 183.495145631068,
                        "std": 78.88572944162593,
                        "min": 150.0,
                        "25%": 150.0,
                        "50%": 150.0,
                        "75%": 150.0,
                        "max": 420.0
                    },
                    {
                        "datetime": "2022-11-27 00:00:00",
                        "count": 105.0,
                        "mean": 182.8571428571429,
                        "std": 78.25886882296824,
                        "min": 150.0,
                        "25%": 150.0,
                        "50%": 150.0,
                        "75%": 150.0,
                        "max": 420.0
                    },
                    {
                        "datetime": "2022-11-28 00:00:00",
                        "count": 115.0,
                        "mean": 174.7826086956522,
                        "std": 70.06698331617929,
                        "min": 150.0,
                        "25%": 150.0,
                        "50%": 150.0,
                        "75%": 150.0,
                        "max": 420.0
                    },
                    {
                        "datetime": "2022-11-29 00:00:00",
                        "count": 114.0,
                        "mean": 173.24561403508773,
                        "std": 68.40141299108627,
                        "min": 150.0,
                        "25%": 150.0,
                        "50%": 150.0,
                        "75%": 150.0,
                        "max": 420.0
                    },
                    {
                        "datetime": "2022-11-30 00:00:00",
                        "count": 112.0,
                        "mean": 171.60714285714286,
                        "std": 66.10874976405768,
                        "min": 150.0,
                        "25%": 150.0,
                        "50%": 150.0,
                        "75%": 150.0,
                        "max": 420.0
                    },
                    {
                        "datetime": "2022-12-01 00:00:00",
                        "count": 116.0,
                        "mean": 178.79310344827587,
                        "std": 75.34448622293405,
                        "min": 150.0,
                        "25%": 150.0,
                        "50%": 150.0,
                        "75%": 150.0,
                        "max": 420.0
                    },
                    {
                        "datetime": "2022-12-02 00:00:00",
                        "count": 115.0,
                        "mean": 179.30434782608697,
                        "std": 76.2696249019554,
                        "min": 150.0,
                        "25%": 150.0,
                        "50%": 150.0,
                        "75%": 150.0,
                        "max": 420.0
                    }
                ]
            },
            "diff": {
                "count": 7,
                "data": [
                    {
                        "datetime": "2022-11-26 00:00:00",
                        "count": null,
                        "mean": null,
                        "std": null,
                        "min": null,
                        "25%": null,
                        "50%": null,
                        "75%": null,
                        "max": null
                    },
                    {
                        "datetime": "2022-11-27 00:00:00",
                        "count": 2.0,
                        "mean": -0.6380027739251091,
                        "std": -0.6268606186576875,
                        "min": 0.0,
                        "25%": 0.0,
                        "50%": 0.0,
                        "75%": 0.0,
                        "max": 0.0
                    },
                    {
                        "datetime": "2022-11-28 00:00:00",
                        "count": 10.0,
                        "mean": -8.074534161490703,
                        "std": -8.19188550678895,
                        "min": 0.0,
                        "25%": 0.0,
                        "50%": 0.0,
                        "75%": 0.0,
                        "max": 0.0
                    },
                    {
                        "datetime": "2022-11-29 00:00:00",
                        "count": -1.0,
                        "mean": -1.53699466056446,
                        "std": -1.6655703250930145,
                        "min": 0.0,
                        "25%": 0.0,
                        "50%": 0.0,
                        "75%": 0.0,
                        "max": 0.0
                    },
                    {
                        "datetime": "2022-11-30 00:00:00",
                        "count": -2.0,
                        "mean": -1.638471177944865,
                        "std": -2.292663227028598,
                        "min": 0.0,
                        "25%": 0.0,
                        "50%": 0.0,
                        "75%": 0.0,
                        "max": 0.0
                    },
                    {
                        "datetime": "2022-12-01 00:00:00",
                        "count": 4.0,
                        "mean": 7.185960591133011,
                        "std": 9.235736458876374,
                        "min": 0.0,
                        "25%": 0.0,
                        "50%": 0.0,
                        "75%": 0.0,
                        "max": 0.0
                    },
                    {
                        "datetime": "2022-12-02 00:00:00",
                        "count": -1.0,
                        "mean": 0.5112443778110958,
                        "std": 0.9251386790213445,
                        "min": 0.0,
                        "25%": 0.0,
                        "50%": 0.0,
                        "75%": 0.0,
                        "max": 0.0
                    }
                ]
            }
        },
        "halfYear": {
            "archive": {
                "count": 13,
                "data": [
                    {
                        "datetime": "2022-06-17 00:00:00",
                        "count": 0.0,
                        "mean": 0.0,
                        "std": 0.0,
                        "min": 0.0,
                        "25%": 0.0,
                        "50%": 0.0,
                        "75%": 0.0,
                        "max": 0.0
                    },
                    {
                        "datetime": "2022-07-01 00:00:00",
                        "count": 0.0,
                        "mean": 0.0,
                        "std": 0.0,
                        "min": 0.0,
                        "25%": 0.0,
                        "50%": 0.0,
                        "75%": 0.0,
                        "max": 0.0
                    },
                    {
                        "datetime": "2022-07-15 00:00:00",
                        "count": 0.0,
                        "mean": 0.0,
                        "std": 0.0,
                        "min": 0.0,
                        "25%": 0.0,
                        "50%": 0.0,
                        "75%": 0.0,
                        "max": 0.0
                    },
                    {
                        "datetime": "2022-07-29 00:00:00",
                        "count": 0.0,
                        "mean": 0.0,
                        "std": 0.0,
                        "min": 0.0,
                        "25%": 0.0,
                        "50%": 0.0,
                        "75%": 0.0,
                        "max": 0.0
                    },
                    {
                        "datetime": "2022-08-12 00:00:00",
                        "count": 0.0,
                        "mean": 0.0,
                        "std": 0.0,
                        "min": 0.0,
                        "25%": 0.0,
                        "50%": 0.0,
                        "75%": 0.0,
                        "max": 0.0
                    },
                    {
                        "datetime": "2022-08-26 00:00:00",
                        "count": 139.0,
                        "mean": 440.863309352518,
                        "std": 40.13531486252167,
                        "min": 400.0,
                        "25%": 400.0,
                        "50%": 480.0,
                        "75%": 480.0,
                        "max": 480.0
                    },
                    {
                        "datetime": "2022-09-09 00:00:00",
                        "count": 169.0,
                        "mean": 430.88757396449705,
                        "std": 43.80468445713132,
                        "min": 180.0,
                        "25%": 400.0,
                        "50%": 400.0,
                        "75%": 480.0,
                        "max": 480.0
                    },
                    {
                        "datetime": "2022-09-23 00:00:00",
                        "count": 157.0,
                        "mean": 286.62420382165607,
                        "std": 163.06186548216078,
                        "min": 150.0,
                        "25%": 150.0,
                        "50%": 150.0,
                        "75%": 480.0,
                        "max": 480.0
                    },
                    {
                        "datetime": "2022-10-07 00:00:00",
                        "count": 144.0,
                        "mean": 287.5,
                        "std": 163.2600568229907,
                        "min": 150.0,
                        "25%": 150.0,
                        "50%": 150.0,
                        "75%": 480.0,
                        "max": 480.0
                    },
                    {
                        "datetime": "2022-10-21 00:00:00",
                        "count": 140.0,
                        "mean": 263.1428571428572,
                        "std": 157.2016334067011,
                        "min": 150.0,
                        "25%": 150.0,
                        "50%": 150.0,
                        "75%": 480.0,
                        "max": 480.0
                    },
                    {
                        "datetime": "2022-11-04 00:00:00",
                        "count": 118.0,
                        "mean": 245.08474576271183,
                        "std": 150.09253990305513,
                        "min": 150.0,
                        "25%": 150.0,
                        "50%": 150.0,
                        "75%": 480.0,
                        "max": 480.0
                    },
                    {
                        "datetime": "2022-11-18 00:00:00",
                        "count": 135.0,
                        "mean": 227.40740740740745,
                        "std": 106.44151195426012,
                        "min": 150.0,
                        "25%": 150.0,
                        "50%": 150.0,
                        "75%": 380.0,
                        "max": 380.0
                    },
                    {
                        "datetime": "2022-12-02 00:00:00",
                        "count": 115.0,
                        "mean": 179.30434782608697,
                        "std": 76.2696249019554,
                        "min": 150.0,
                        "25%": 150.0,
                        "50%": 150.0,
                        "75%": 150.0,
                        "max": 420.0
                    }
                ]
            },
            "diff": {
                "count": 13,
                "data": [
                    {
                        "datetime": "2022-06-17 00:00:00",
                        "count": null,
                        "mean": null,
                        "std": null,
                        "min": null,
                        "25%": null,
                        "50%": null,
                        "75%": null,
                        "max": null
                    },
                    {
                        "datetime": "2022-07-01 00:00:00",
                        "count": 0.0,
                        "mean": 0.0,
                        "std": 0.0,
                        "min": 0.0,
                        "25%": 0.0,
                        "50%": 0.0,
                        "75%": 0.0,
                        "max": 0.0
                    },
                    {
                        "datetime": "2022-07-15 00:00:00",
                        "count": 0.0,
                        "mean": 0.0,
                        "std": 0.0,
                        "min": 0.0,
                        "25%": 0.0,
                        "50%": 0.0,
                        "75%": 0.0,
                        "max": 0.0
                    },
                    {
                        "datetime": "2022-07-29 00:00:00",
                        "count": 0.0,
                        "mean": 0.0,
                        "std": 0.0,
                        "min": 0.0,
                        "25%": 0.0,
                        "50%": 0.0,
                        "75%": 0.0,
                        "max": 0.0
                    },
                    {
                        "datetime": "2022-08-12 00:00:00",
                        "count": 0.0,
                        "mean": 0.0,
                        "std": 0.0,
                        "min": 0.0,
                        "25%": 0.0,
                        "50%": 0.0,
                        "75%": 0.0,
                        "max": 0.0
                    },
                    {
                        "datetime": "2022-08-26 00:00:00",
                        "count": 139.0,
                        "mean": 440.863309352518,
                        "std": 40.13531486252167,
                        "min": 400.0,
                        "25%": 400.0,
                        "50%": 480.0,
                        "75%": 480.0,
                        "max": 480.0
                    },
                    {
                        "datetime": "2022-09-09 00:00:00",
                        "count": 30.0,
                        "mean": -9.97573538802095,
                        "std": 3.6693695946096554,
                        "min": -220.0,
                        "25%": 0.0,
                        "50%": -80.0,
                        "75%": 0.0,
                        "max": 0.0
                    },
                    {
                        "datetime": "2022-09-23 00:00:00",
                        "count": -12.0,
                        "mean": -144.26337014284098,
                        "std": 119.25718102502947,
                        "min": -30.0,
                        "25%": -250.0,
                        "50%": -250.0,
                        "75%": 0.0,
                        "max": 0.0
                    },
                    {
                        "datetime": "2022-10-07 00:00:00",
                        "count": -13.0,
                        "mean": 0.8757961783439328,
                        "std": 0.19819134082990786,
                        "min": 0.0,
                        "25%": 0.0,
                        "50%": 0.0,
                        "75%": 0.0,
                        "max": 0.0
                    },
                    {
                        "datetime": "2022-10-21 00:00:00",
                        "count": -4.0,
                        "mean": -24.357142857142776,
                        "std": -6.0584234162896,
                        "min": 0.0,
                        "25%": 0.0,
                        "50%": 0.0,
                        "75%": 0.0,
                        "max": 0.0
                    },
                    {
                        "datetime": "2022-11-04 00:00:00",
                        "count": -22.0,
                        "mean": -18.05811138014539,
                        "std": -7.1090935036459655,
                        "min": 0.0,
                        "25%": 0.0,
                        "50%": 0.0,
                        "75%": 0.0,
                        "max": 0.0
                    },
                    {
                        "datetime": "2022-11-18 00:00:00",
                        "count": 17.0,
                        "mean": -17.677338355304386,
                        "std": -43.651027948795004,
                        "min": 0.0,
                        "25%": 0.0,
                        "50%": 0.0,
                        "75%": -100.0,
                        "max": -100.0
                    },
                    {
                        "datetime": "2022-12-02 00:00:00",
                        "count": -20.0,
                        "mean": -48.10305958132048,
                        "std": -30.171887052304726,
                        "min": 0.0,
                        "25%": 0.0,
                        "50%": 0.0,
                        "75%": -230.0,
                        "max": 40.0
                    }
                ]
            }
        },
        "OneYear": {
            "archive": {
                "count": 0,
                "data": []
            },
            "diff": {
                "count": 0,
                "data": []
            }
        }
    },
    "calc": {
        "latest_date": "2022-12-02 00:00:00",
        "updated_at": "2022-12-02 20:02:07"
    }
}