{
    "price": {
        "current": {
            "datetime": "2022-12-06 00:00:00",
            "count": 6.0,
            "mean": 765.8333333333334,
            "std": 34.701104689428355,
            "min": 695.0,
            "25%": 780.0,
            "50%": 780.0,
            "75%": 780.0,
            "max": 780.0
        },
        "summary7Days": {
            "datetime": "2022-12-06 00:00:00",
            "count": 0.0,
            "mean": -0.16666666666662877,
            "std": 0.4082482904638596,
            "min": -1.0,
            "25%": 0.0,
            "50%": 0.0,
            "75%": 0.0,
            "max": 0.0
        },
        "volatility": {
            "weekly": {
                "min": {
                    "basePrice": 696.0,
                    "latestPrice": 695.0,
                    "percent": -0.14
                },
                "50%": {
                    "basePrice": 780.0,
                    "latestPrice": 780.0,
                    "percent": 0.0
                }
            },
            "daily": {
                "min": {
                    "basePrice": 695.0,
                    "latestPrice": 695.0,
                    "percent": 0.0
                },
                "50%": {
                    "basePrice": 780.0,
                    "latestPrice": 780.0,
                    "percent": 0.0
                }
            }
        },
        "weekly": {
            "archive": {
                "count": 7,
                "data": [
                    {
                        "datetime": "2022-11-30 00:00:00",
                        "count": 6.0,
                        "mean": 766.0,
                        "std": 34.292856398964496,
                        "min": 696.0,
                        "25%": 780.0,
                        "50%": 780.0,
                        "75%": 780.0,
                        "max": 780.0
                    },
                    {
                        "datetime": "2022-12-01 00:00:00",
                        "count": 6.0,
                        "mean": 766.0,
                        "std": 34.292856398964496,
                        "min": 696.0,
                        "25%": 780.0,
                        "50%": 780.0,
                        "75%": 780.0,
                        "max": 780.0
                    },
                    {
                        "datetime": "2022-12-02 00:00:00",
                        "count": 6.0,
                        "mean": 766.0,
                        "std": 34.292856398964496,
                        "min": 696.0,
                        "25%": 780.0,
                        "50%": 780.0,
                        "75%": 780.0,
                        "max": 780.0
                    },
                    {
                        "datetime": "2022-12-03 00:00:00",
                        "count": 6.0,
                        "mean": 766.0,
                        "std": 34.292856398964496,
                        "min": 696.0,
                        "25%": 780.0,
                        "50%": 780.0,
                        "75%": 780.0,
                        "max": 780.0
                    },
                    {
                        "datetime": "2022-12-04 00:00:00",
                        "count": 6.0,
                        "mean": 765.8333333333334,
                        "std": 34.701104689428355,
                        "min": 695.0,
                        "25%": 780.0,
                        "50%": 780.0,
                        "75%": 780.0,
                        "max": 780.0
                    },
                    {
                        "datetime": "2022-12-05 00:00:00",
                        "count": 6.0,
                        "mean": 765.8333333333334,
                        "std": 34.701104689428355,
                        "min": 695.0,
                        "25%": 780.0,
                        "50%": 780.0,
                        "75%": 780.0,
                        "max": 780.0
                    },
                    {
                        "datetime": "2022-12-06 00:00:00",
                        "count": 6.0,
                        "mean": 765.8333333333334,
                        "std": 34.701104689428355,
                        "min": 695.0,
                        "25%": 780.0,
                        "50%": 780.0,
                        "75%": 780.0,
                        "max": 780.0
                    }
                ]
            },
            "diff": {
                "count": 7,
                "data": [
                    {
                        "datetime": "2022-11-30 00:00:00",
                        "count": null,
                        "mean": null,
                        "std": null,
                        "min": null,
                        "25%": null,
                        "50%": null,
                        "75%": null,
                        "max": null
                    },
                    {
                        "datetime": "2022-12-01 00:00:00",
                        "count": 0.0,
                        "mean": 0.0,
                        "std": 0.0,
                        "min": 0.0,
                        "25%": 0.0,
                        "50%": 0.0,
                        "75%": 0.0,
                        "max": 0.0
                    },
                    {
                        "datetime": "2022-12-02 00:00:00",
                        "count": 0.0,
                        "mean": 0.0,
                        "std": 0.0,
                        "min": 0.0,
                        "25%": 0.0,
                        "50%": 0.0,
                        "75%": 0.0,
                        "max": 0.0
                    },
                    {
                        "datetime": "2022-12-03 00:00:00",
                        "count": 0.0,
                        "mean": 0.0,
                        "std": 0.0,
                        "min": 0.0,
                        "25%": 0.0,
                        "50%": 0.0,
                        "75%": 0.0,
                        "max": 0.0
                    },
                    {
                        "datetime": "2022-12-04 00:00:00",
                        "count": 0.0,
                        "mean": -0.16666666666662877,
                        "std": 0.4082482904638596,
                        "min": -1.0,
                        "25%": 0.0,
                        "50%": 0.0,
                        "75%": 0.0,
                        "max": 0.0
                    },
                    {
                        "datetime": "2022-12-05 00:00:00",
                        "count": 0.0,
                        "mean": 0.0,
                        "std": 0.0,
                        "min": 0.0,
                        "25%": 0.0,
                        "50%": 0.0,
                        "75%": 0.0,
                        "max": 0.0
                    },
                    {
                        "datetime": "2022-12-06 00:00:00",
                        "count": 0.0,
                        "mean": 0.0,
                        "std": 0.0,
                        "min": 0.0,
                        "25%": 0.0,
                        "50%": 0.0,
                        "75%": 0.0,
                        "max": 0.0
                    }
                ]
            }
        },
        "halfYear": {
            "archive": {
                "count": 13,
                "data": [
                    {
                        "datetime": "2022-06-21 00:00:00",
                        "count": 0.0,
                        "mean": 0.0,
                        "std": 0.0,
                        "min": 0.0,
                        "25%": 0.0,
                        "50%": 0.0,
                        "75%": 0.0,
                        "max": 0.0
                    },
                    {
                        "datetime": "2022-07-05 00:00:00",
                        "count": 0.0,
                        "mean": 0.0,
                        "std": 0.0,
                        "min": 0.0,
                        "25%": 0.0,
                        "50%": 0.0,
                        "75%": 0.0,
                        "max": 0.0
                    },
                    {
                        "datetime": "2022-07-19 00:00:00",
                        "count": 0.0,
                        "mean": 0.0,
                        "std": 0.0,
                        "min": 0.0,
                        "25%": 0.0,
                        "50%": 0.0,
                        "75%": 0.0,
                        "max": 0.0
                    },
                    {
                        "datetime": "2022-08-02 00:00:00",
                        "count": 0.0,
                        "mean": 0.0,
                        "std": 0.0,
                        "min": 0.0,
                        "25%": 0.0,
                        "50%": 0.0,
                        "75%": 0.0,
                        "max": 0.0
                    },
                    {
                        "datetime": "2022-08-16 00:00:00",
                        "count": 0.0,
                        "mean": 0.0,
                        "std": 0.0,
                        "min": 0.0,
                        "25%": 0.0,
                        "50%": 0.0,
                        "75%": 0.0,
                        "max": 0.0
                    },
                    {
                        "datetime": "2022-08-30 00:00:00",
                        "count": 0.0,
                        "mean": 0.0,
                        "std": 0.0,
                        "min": 0.0,
                        "25%": 0.0,
                        "50%": 0.0,
                        "75%": 0.0,
                        "max": 0.0
                    },
                    {
                        "datetime": "2022-09-13 00:00:00",
                        "count": 13.0,
                        "mean": 736.9230769230769,
                        "std": 48.88500373062878,
                        "min": 680.0,
                        "25%": 680.0,
                        "50%": 780.0,
                        "75%": 780.0,
                        "max": 780.0
                    },
                    {
                        "datetime": "2022-09-27 00:00:00",
                        "count": 19.0,
                        "mean": 750.5263157894736,
                        "std": 44.90405626450519,
                        "min": 680.0,
                        "25%": 700.0,
                        "50%": 780.0,
                        "75%": 780.0,
                        "max": 780.0
                    },
                    {
                        "datetime": "2022-10-11 00:00:00",
                        "count": 22.0,
                        "mean": 742.7272727272727,
                        "std": 46.3097046480405,
                        "min": 680.0,
                        "25%": 700.0,
                        "50%": 780.0,
                        "75%": 780.0,
                        "max": 780.0
                    },
                    {
                        "datetime": "2022-10-25 00:00:00",
                        "count": 14.0,
                        "mean": 728.5714285714286,
                        "std": 46.88072309384955,
                        "min": 680.0,
                        "25%": 685.0,
                        "50%": 700.0,
                        "75%": 780.0,
                        "max": 780.0
                    },
                    {
                        "datetime": "2022-11-08 00:00:00",
                        "count": 18.0,
                        "mean": 728.8888888888889,
                        "std": 47.6369714166595,
                        "min": 680.0,
                        "25%": 680.0,
                        "50%": 700.0,
                        "75%": 780.0,
                        "max": 780.0
                    },
                    {
                        "datetime": "2022-11-22 00:00:00",
                        "count": 32.0,
                        "mean": 734.3125,
                        "std": 46.94845320204401,
                        "min": 680.0,
                        "25%": 680.0,
                        "50%": 740.0,
                        "75%": 780.0,
                        "max": 780.0
                    },
                    {
                        "datetime": "2022-12-06 00:00:00",
                        "count": 6.0,
                        "mean": 765.8333333333334,
                        "std": 34.701104689428355,
                        "min": 695.0,
                        "25%": 780.0,
                        "50%": 780.0,
                        "75%": 780.0,
                        "max": 780.0
                    }
                ]
            },
            "diff": {
                "count": 13,
                "data": [
                    {
                        "datetime": "2022-06-21 00:00:00",
                        "count": null,
                        "mean": null,
                        "std": null,
                        "min": null,
                        "25%": null,
                        "50%": null,
                        "75%": null,
                        "max": null
                    },
                    {
                        "datetime": "2022-07-05 00:00:00",
                        "count": 0.0,
                        "mean": 0.0,
                        "std": 0.0,
                        "min": 0.0,
                        "25%": 0.0,
                        "50%": 0.0,
                        "75%": 0.0,
                        "max": 0.0
                    },
                    {
                        "datetime": "2022-07-19 00:00:00",
                        "count": 0.0,
                        "mean": 0.0,
                        "std": 0.0,
                        "min": 0.0,
                        "25%": 0.0,
                        "50%": 0.0,
                        "75%": 0.0,
                        "max": 0.0
                    },
                    {
                        "datetime": "2022-08-02 00:00:00",
                        "count": 0.0,
                        "mean": 0.0,
                        "std": 0.0,
                        "min": 0.0,
                        "25%": 0.0,
                        "50%": 0.0,
                        "75%": 0.0,
                        "max": 0.0
                    },
                    {
                        "datetime": "2022-08-16 00:00:00",
                        "count": 0.0,
                        "mean": 0.0,
                        "std": 0.0,
                        "min": 0.0,
                        "25%": 0.0,
                        "50%": 0.0,
                        "75%": 0.0,
                        "max": 0.0
                    },
                    {
                        "datetime": "2022-08-30 00:00:00",
                        "count": 0.0,
                        "mean": 0.0,
                        "std": 0.0,
                        "min": 0.0,
                        "25%": 0.0,
                        "50%": 0.0,
                        "75%": 0.0,
                        "max": 0.0
                    },
                    {
                        "datetime": "2022-09-13 00:00:00",
                        "count": 13.0,
                        "mean": 736.9230769230769,
                        "std": 48.88500373062878,
                        "min": 680.0,
                        "25%": 680.0,
                        "50%": 780.0,
                        "75%": 780.0,
                        "max": 780.0
                    },
                    {
                        "datetime": "2022-09-27 00:00:00",
                        "count": 6.0,
                        "mean": 13.603238866396737,
                        "std": -3.980947466123588,
                        "min": 0.0,
                        "25%": 20.0,
                        "50%": 0.0,
                        "75%": 0.0,
                        "max": 0.0
                    },
                    {
                        "datetime": "2022-10-11 00:00:00",
                        "count": 3.0,
                        "mean": -7.799043062200894,
                        "std": 1.4056483835353077,
                        "min": 0.0,
                        "25%": 0.0,
                        "50%": 0.0,
                        "75%": 0.0,
                        "max": 0.0
                    },
                    {
                        "datetime": "2022-10-25 00:00:00",
                        "count": -8.0,
                        "mean": -14.155844155844193,
                        "std": 0.5710184458090453,
                        "min": 0.0,
                        "25%": -15.0,
                        "50%": -80.0,
                        "75%": 0.0,
                        "max": 0.0
                    },
                    {
                        "datetime": "2022-11-08 00:00:00",
                        "count": 4.0,
                        "mean": 0.31746031746035897,
                        "std": 0.7562483228099524,
                        "min": 0.0,
                        "25%": -5.0,
                        "50%": 0.0,
                        "75%": 0.0,
                        "max": 0.0
                    },
                    {
                        "datetime": "2022-11-22 00:00:00",
                        "count": 14.0,
                        "mean": 5.423611111111086,
                        "std": -0.6885182146154918,
                        "min": 0.0,
                        "25%": 0.0,
                        "50%": 40.0,
                        "75%": 0.0,
                        "max": 0.0
                    },
                    {
                        "datetime": "2022-12-06 00:00:00",
                        "count": -26.0,
                        "mean": 31.52083333333337,
                        "std": -12.247348512615652,
                        "min": 15.0,
                        "25%": 100.0,
                        "50%": 40.0,
                        "75%": 0.0,
                        "max": 0.0
                    }
                ]
            }
        },
        "OneYear": {
            "archive": {
                "count": 0,
                "data": []
            },
            "diff": {
                "count": 0,
                "data": []
            }
        }
    },
    "calc": {
        "latest_date": "2022-12-06 00:00:00",
        "updated_at": "2022-12-06 20:03:02"
    }
}