{
    "price": {
        "current": {
            "datetime": "2022-12-15 00:00:00",
            "count": 2.0,
            "mean": 330.0,
            "std": 0.0,
            "min": 330.0,
            "25%": 330.0,
            "50%": 330.0,
            "75%": 330.0,
            "max": 330.0
        },
        "summary7Days": {
            "datetime": "2022-12-15 00:00:00",
            "count": -1.0,
            "mean": -23.333333333333314,
            "std": -40.41451884327381,
            "min": 0.0,
            "25%": 0.0,
            "50%": 0.0,
            "75%": -35.0,
            "max": -70.0
        },
        "volatility": {
            "weekly": {
                "min": {
                    "basePrice": 330.0,
                    "latestPrice": 330.0,
                    "percent": 0.0
                },
                "50%": {
                    "basePrice": 330.0,
                    "latestPrice": 330.0,
                    "percent": 0.0
                }
            },
            "daily": {
                "min": {
                    "basePrice": 330.0,
                    "latestPrice": 330.0,
                    "percent": 0.0
                },
                "50%": {
                    "basePrice": 330.0,
                    "latestPrice": 330.0,
                    "percent": 0.0
                }
            }
        },
        "weekly": {
            "archive": {
                "count": 7,
                "data": [
                    {
                        "datetime": "2022-12-09 00:00:00",
                        "count": 3.0,
                        "mean": 353.3333333333333,
                        "std": 40.41451884327381,
                        "min": 330.0,
                        "25%": 330.0,
                        "50%": 330.0,
                        "75%": 365.0,
                        "max": 400.0
                    },
                    {
                        "datetime": "2022-12-10 00:00:00",
                        "count": 2.0,
                        "mean": 330.0,
                        "std": 0.0,
                        "min": 330.0,
                        "25%": 330.0,
                        "50%": 330.0,
                        "75%": 330.0,
                        "max": 330.0
                    },
                    {
                        "datetime": "2022-12-11 00:00:00",
                        "count": 2.0,
                        "mean": 330.0,
                        "std": 0.0,
                        "min": 330.0,
                        "25%": 330.0,
                        "50%": 330.0,
                        "75%": 330.0,
                        "max": 330.0
                    },
                    {
                        "datetime": "2022-12-12 00:00:00",
                        "count": 2.0,
                        "mean": 330.0,
                        "std": 0.0,
                        "min": 330.0,
                        "25%": 330.0,
                        "50%": 330.0,
                        "75%": 330.0,
                        "max": 330.0
                    },
                    {
                        "datetime": "2022-12-13 00:00:00",
                        "count": 3.0,
                        "mean": 353.3333333333333,
                        "std": 40.41451884327381,
                        "min": 330.0,
                        "25%": 330.0,
                        "50%": 330.0,
                        "75%": 365.0,
                        "max": 400.0
                    },
                    {
                        "datetime": "2022-12-14 00:00:00",
                        "count": 2.0,
                        "mean": 330.0,
                        "std": 0.0,
                        "min": 330.0,
                        "25%": 330.0,
                        "50%": 330.0,
                        "75%": 330.0,
                        "max": 330.0
                    },
                    {
                        "datetime": "2022-12-15 00:00:00",
                        "count": 2.0,
                        "mean": 330.0,
                        "std": 0.0,
                        "min": 330.0,
                        "25%": 330.0,
                        "50%": 330.0,
                        "75%": 330.0,
                        "max": 330.0
                    }
                ]
            },
            "diff": {
                "count": 7,
                "data": [
                    {
                        "datetime": "2022-12-09 00:00:00",
                        "count": null,
                        "mean": null,
                        "std": null,
                        "min": null,
                        "25%": null,
                        "50%": null,
                        "75%": null,
                        "max": null
                    },
                    {
                        "datetime": "2022-12-10 00:00:00",
                        "count": -1.0,
                        "mean": -23.333333333333314,
                        "std": -40.41451884327381,
                        "min": 0.0,
                        "25%": 0.0,
                        "50%": 0.0,
                        "75%": -35.0,
                        "max": -70.0
                    },
                    {
                        "datetime": "2022-12-11 00:00:00",
                        "count": 0.0,
                        "mean": 0.0,
                        "std": 0.0,
                        "min": 0.0,
                        "25%": 0.0,
                        "50%": 0.0,
                        "75%": 0.0,
                        "max": 0.0
                    },
                    {
                        "datetime": "2022-12-12 00:00:00",
                        "count": 0.0,
                        "mean": 0.0,
                        "std": 0.0,
                        "min": 0.0,
                        "25%": 0.0,
                        "50%": 0.0,
                        "75%": 0.0,
                        "max": 0.0
                    },
                    {
                        "datetime": "2022-12-13 00:00:00",
                        "count": 1.0,
                        "mean": 23.333333333333314,
                        "std": 40.41451884327381,
                        "min": 0.0,
                        "25%": 0.0,
                        "50%": 0.0,
                        "75%": 35.0,
                        "max": 70.0
                    },
                    {
                        "datetime": "2022-12-14 00:00:00",
                        "count": -1.0,
                        "mean": -23.333333333333314,
                        "std": -40.41451884327381,
                        "min": 0.0,
                        "25%": 0.0,
                        "50%": 0.0,
                        "75%": -35.0,
                        "max": -70.0
                    },
                    {
                        "datetime": "2022-12-15 00:00:00",
                        "count": 0.0,
                        "mean": 0.0,
                        "std": 0.0,
                        "min": 0.0,
                        "25%": 0.0,
                        "50%": 0.0,
                        "75%": 0.0,
                        "max": 0.0
                    }
                ]
            }
        },
        "halfYear": {
            "archive": {
                "count": 13,
                "data": [
                    {
                        "datetime": "2022-06-30 00:00:00",
                        "count": 0.0,
                        "mean": 0.0,
                        "std": 0.0,
                        "min": 0.0,
                        "25%": 0.0,
                        "50%": 0.0,
                        "75%": 0.0,
                        "max": 0.0
                    },
                    {
                        "datetime": "2022-07-14 00:00:00",
                        "count": 0.0,
                        "mean": 0.0,
                        "std": 0.0,
                        "min": 0.0,
                        "25%": 0.0,
                        "50%": 0.0,
                        "75%": 0.0,
                        "max": 0.0
                    },
                    {
                        "datetime": "2022-07-28 00:00:00",
                        "count": 0.0,
                        "mean": 0.0,
                        "std": 0.0,
                        "min": 0.0,
                        "25%": 0.0,
                        "50%": 0.0,
                        "75%": 0.0,
                        "max": 0.0
                    },
                    {
                        "datetime": "2022-08-11 00:00:00",
                        "count": 0.0,
                        "mean": 0.0,
                        "std": 0.0,
                        "min": 0.0,
                        "25%": 0.0,
                        "50%": 0.0,
                        "75%": 0.0,
                        "max": 0.0
                    },
                    {
                        "datetime": "2022-08-25 00:00:00",
                        "count": 208.0,
                        "mean": 478.0769230769231,
                        "std": 20.70388995058276,
                        "min": 450.0,
                        "25%": 480.0,
                        "50%": 480.0,
                        "75%": 480.0,
                        "max": 605.0
                    },
                    {
                        "datetime": "2022-09-08 00:00:00",
                        "count": 220.0,
                        "mean": 476.0,
                        "std": 10.310255567298691,
                        "min": 440.0,
                        "25%": 480.0,
                        "50%": 480.0,
                        "75%": 480.0,
                        "max": 480.0
                    },
                    {
                        "datetime": "2022-09-22 00:00:00",
                        "count": 227.0,
                        "mean": 462.4229074889868,
                        "std": 31.027207649383342,
                        "min": 400.0,
                        "25%": 450.0,
                        "50%": 480.0,
                        "75%": 480.0,
                        "max": 480.0
                    },
                    {
                        "datetime": "2022-10-06 00:00:00",
                        "count": 240.0,
                        "mean": 459.7916666666667,
                        "std": 30.60680478754112,
                        "min": 400.0,
                        "25%": 450.0,
                        "50%": 480.0,
                        "75%": 480.0,
                        "max": 480.0
                    },
                    {
                        "datetime": "2022-10-20 00:00:00",
                        "count": 299.0,
                        "mean": 415.4515050167224,
                        "std": 10.6522277379436,
                        "min": 390.0,
                        "25%": 420.0,
                        "50%": 420.0,
                        "75%": 420.0,
                        "max": 440.0
                    },
                    {
                        "datetime": "2022-11-03 00:00:00",
                        "count": 58.0,
                        "mean": 421.3793103448276,
                        "std": 5.112171874107659,
                        "min": 420.0,
                        "25%": 420.0,
                        "50%": 420.0,
                        "75%": 420.0,
                        "max": 440.0
                    },
                    {
                        "datetime": "2022-11-17 00:00:00",
                        "count": 62.0,
                        "mean": 421.9354838709677,
                        "std": 5.9612710927049095,
                        "min": 420.0,
                        "25%": 420.0,
                        "50%": 420.0,
                        "75%": 420.0,
                        "max": 440.0
                    },
                    {
                        "datetime": "2022-12-01 00:00:00",
                        "count": 39.0,
                        "mean": 403.5897435897436,
                        "std": 32.483775665883904,
                        "min": 330.0,
                        "25%": 400.0,
                        "50%": 420.0,
                        "75%": 420.0,
                        "max": 420.0
                    },
                    {
                        "datetime": "2022-12-15 00:00:00",
                        "count": 2.0,
                        "mean": 330.0,
                        "std": 0.0,
                        "min": 330.0,
                        "25%": 330.0,
                        "50%": 330.0,
                        "75%": 330.0,
                        "max": 330.0
                    }
                ]
            },
            "diff": {
                "count": 13,
                "data": [
                    {
                        "datetime": "2022-06-30 00:00:00",
                        "count": null,
                        "mean": null,
                        "std": null,
                        "min": null,
                        "25%": null,
                        "50%": null,
                        "75%": null,
                        "max": null
                    },
                    {
                        "datetime": "2022-07-14 00:00:00",
                        "count": 0.0,
                        "mean": 0.0,
                        "std": 0.0,
                        "min": 0.0,
                        "25%": 0.0,
                        "50%": 0.0,
                        "75%": 0.0,
                        "max": 0.0
                    },
                    {
                        "datetime": "2022-07-28 00:00:00",
                        "count": 0.0,
                        "mean": 0.0,
                        "std": 0.0,
                        "min": 0.0,
                        "25%": 0.0,
                        "50%": 0.0,
                        "75%": 0.0,
                        "max": 0.0
                    },
                    {
                        "datetime": "2022-08-11 00:00:00",
                        "count": 0.0,
                        "mean": 0.0,
                        "std": 0.0,
                        "min": 0.0,
                        "25%": 0.0,
                        "50%": 0.0,
                        "75%": 0.0,
                        "max": 0.0
                    },
                    {
                        "datetime": "2022-08-25 00:00:00",
                        "count": 208.0,
                        "mean": 478.0769230769231,
                        "std": 20.70388995058276,
                        "min": 450.0,
                        "25%": 480.0,
                        "50%": 480.0,
                        "75%": 480.0,
                        "max": 605.0
                    },
                    {
                        "datetime": "2022-09-08 00:00:00",
                        "count": 12.0,
                        "mean": -2.0769230769230944,
                        "std": -10.393634383284068,
                        "min": -10.0,
                        "25%": 0.0,
                        "50%": 0.0,
                        "75%": 0.0,
                        "max": -125.0
                    },
                    {
                        "datetime": "2022-09-22 00:00:00",
                        "count": 7.0,
                        "mean": -13.577092511013177,
                        "std": 20.716952082084653,
                        "min": -40.0,
                        "25%": -30.0,
                        "50%": 0.0,
                        "75%": 0.0,
                        "max": 0.0
                    },
                    {
                        "datetime": "2022-10-06 00:00:00",
                        "count": 13.0,
                        "mean": -2.6312408223201373,
                        "std": -0.42040286184222353,
                        "min": 0.0,
                        "25%": 0.0,
                        "50%": 0.0,
                        "75%": 0.0,
                        "max": 0.0
                    },
                    {
                        "datetime": "2022-10-20 00:00:00",
                        "count": 59.0,
                        "mean": -44.340161649944264,
                        "std": -19.954577049597518,
                        "min": -10.0,
                        "25%": -30.0,
                        "50%": -60.0,
                        "75%": -60.0,
                        "max": -40.0
                    },
                    {
                        "datetime": "2022-11-03 00:00:00",
                        "count": -241.0,
                        "mean": 5.927805328105194,
                        "std": -5.54005586383594,
                        "min": 30.0,
                        "25%": 0.0,
                        "50%": 0.0,
                        "75%": 0.0,
                        "max": 0.0
                    },
                    {
                        "datetime": "2022-11-17 00:00:00",
                        "count": 4.0,
                        "mean": 0.5561735261400713,
                        "std": 0.8490992185972503,
                        "min": 0.0,
                        "25%": 0.0,
                        "50%": 0.0,
                        "75%": 0.0,
                        "max": 0.0
                    },
                    {
                        "datetime": "2022-12-01 00:00:00",
                        "count": -23.0,
                        "mean": -18.345740281224096,
                        "std": 26.522504573178995,
                        "min": -90.0,
                        "25%": -20.0,
                        "50%": 0.0,
                        "75%": 0.0,
                        "max": -20.0
                    },
                    {
                        "datetime": "2022-12-15 00:00:00",
                        "count": -37.0,
                        "mean": -73.58974358974359,
                        "std": -32.483775665883904,
                        "min": 0.0,
                        "25%": -70.0,
                        "50%": -90.0,
                        "75%": -90.0,
                        "max": -90.0
                    }
                ]
            }
        },
        "OneYear": {
            "archive": {
                "count": 0,
                "data": []
            },
            "diff": {
                "count": 0,
                "data": []
            }
        }
    },
    "calc": {
        "latest_date": "2022-12-15 00:00:00",
        "updated_at": "2022-12-15 20:02:07"
    }
}